moyan/__init__.py
moyan/convert_img_lmdb.py
moyan/tools.py
moyan/augment/__init__.py
moyan/augment/autoaugment.py
moyan/augment/cutout.py
moyan/decorator/__init__.py
moyan/decorator/time.py
moyan/dettools/__init__.py
moyan/dettools/coco_to_voc.py
moyan/dettools/convert_widerperson_to_voc.py
moyan/dettools/voc_to_coco.py
moyan/dettools/voc_to_yolo.py
moyan/dettools/xml_utils.py
moyan/pai/__init__.py
moyan/pai/convert_swf_data.py
moyan/pai/openai_api.py
moyan/segtools/__init__.py
moyan/segtools/gray28bit.py
moyan/segtools/labelme_json_to_png.py
moyan/segtools/tools.py
moyan/segtools/vis_mask.py
moyan/template/TFLite.py
moyan/template/TorchScript.py
moyan/template/WarpUtil.py
moyan/template/__init__.py
moyan/template/pb_model.py
moyan/template/ssd_tflite.py
test/InfinityMM_data.py
test/TFCKPT.py
test/TFLite.py
test/Torchscript.py
test/__init__.py
test/chatgpt_test.py
test/coco_json_vis.py
test/convert_instruction_swift.py
test/convert_tflite_fp32_to_fp16.py
test/create_num.py
test/del_tools.py
test/fillter_chinese_img.py
test/from_file_move_file.py
test/generate_trainval_txt.py
test/lableme_and_paddleocr.py
test/langchain_test.py
test/lmdb_merge.py
test/lmdb_to_image.py
test/load_modelscope_data.py
test/make_lmdb.py
test/model.py
test/normalization_manul.py
test/ocr_dict.py
test/onnx_to_fp16.py
test/pdf2img.py
test/ppocr.py
test/ppocr_calculate_acc.py
test/ppocr_layoutlm copy.py
test/ppocr_layoutlm.py
test/quanjiao_to_banjiao.py
test/remove_chinese_mark.py
test/rewrite_ocr_datat_gt_label.py
test/run_mmseg_tflite.py
test/run_paddleocr_tflite.py
test/self_attention.py
test/show_lmdb.py
test/test.py
test/test_crop.py
test/tflite_ssd.py
test/torch_style_lmdb_dataset.py
test/video_face_recognition.py
test/video_face_recognition_clip.py
test/voc_mask_to_coco.py
test/卡证多轮对话模板.py
moyan-1.3.5.dist-info/METADATA
moyan-1.3.5.dist-info/WHEEL
moyan-1.3.5.dist-info/top_level.txt
moyan-1.3.5.dist-info/RECORD
